python_scripttease-7.2.0.dist-info/licenses/LICENSE.txt
scripttease/__init__.py
scripttease/constants.py
scripttease/exceptions.py
scripttease/variables.py
scripttease/version.py
scripttease/cli/__init__.py
scripttease/cli/initialize.py
scripttease/cli/subcommands.py
scripttease/lib/__init__.py
scripttease/lib/contexts.py
scripttease/lib/factories.py
scripttease/lib/commands/__init__.py
scripttease/lib/commands/base.py
scripttease/lib/commands/centos.py
scripttease/lib/commands/django.py
scripttease/lib/commands/messages.py
scripttease/lib/commands/mysql.py
scripttease/lib/commands/pgsql.py
scripttease/lib/commands/php.py
scripttease/lib/commands/posix.py
scripttease/lib/commands/python.py
scripttease/lib/commands/ubuntu.py
scripttease/lib/loaders/__init__.py
scripttease/lib/loaders/base.py
scripttease/lib/loaders/ini.py
scripttease/lib/loaders/yaml.py
python_scripttease-7.2.0.dist-info/METADATA
python_scripttease-7.2.0.dist-info/WHEEL
python_scripttease-7.2.0.dist-info/entry_points.txt
python_scripttease-7.2.0.dist-info/top_level.txt
python_scripttease-7.2.0.dist-info/RECORD
